pgptracker/__init__.py
pgptracker/cli/__init__.py
pgptracker/cli/__main__.py
pgptracker/cli/cli.py
pgptracker/cli/interactive.py
pgptracker/cli/subcommands.py
pgptracker/databases/pathways_plabase.txt
pgptracker/environments/picrust2.yml
pgptracker/environments/qiime2-amplicon-2025.10.yml
pgptracker/stage1_processing/__init__.py
pgptracker/stage1_processing/gen_ko_abun.py
pgptracker/stage1_processing/merge_tax_abun.py
pgptracker/stage1_processing/pipeline_st1.py
pgptracker/stage1_processing/strat_pgpt.py
pgptracker/stage1_processing/unstrat_pgpt.py
pgptracker/stage2_analysis/__init__.py
pgptracker/stage2_analysis/clr_normalize.py
pgptracker/stage2_analysis/clustering_ML.py
pgptracker/stage2_analysis/diversity.py
pgptracker/stage2_analysis/ordination.py
pgptracker/stage2_analysis/pipeline_st2.py
pgptracker/stage2_analysis/plot_funcs.py
pgptracker/stage2_analysis/statistics.py
pgptracker/stage2_analysis/visualizations.py
pgptracker/utils/__init__.py
pgptracker/utils/env_manager.py
pgptracker/utils/validator.py
pgptracker/utils/profiling_tools/__init__.py
pgptracker/utils/profiling_tools/profile_config.py
pgptracker/utils/profiling_tools/profile_reporter.py
pgptracker/utils/profiling_tools/profiler.py
pgptracker/wrappers/__init__.py
pgptracker/wrappers/picrust/__init__.py
pgptracker/wrappers/picrust/hsp_prediction.py
pgptracker/wrappers/picrust/place_seqs.py
pgptracker/wrappers/qiime/__init__.py
pgptracker/wrappers/qiime/classify.py
pgptracker/wrappers/qiime/export_module.py
pgptracker-0.1.3.dist-info/licenses/LICENSE
pgptracker-0.1.3.dist-info/METADATA
pgptracker-0.1.3.dist-info/WHEEL
pgptracker-0.1.3.dist-info/entry_points.txt
pgptracker-0.1.3.dist-info/top_level.txt
pgptracker-0.1.3.dist-info/RECORD
