Metadata-Version: 2.4
Name: pgptracker
Version: 0.1.3
Summary: Integration of soil metagenomic data for correlation of microbial markers with plant biochemical indicators
Home-page: https://github.com/kiuone/PGPTracker
Author: Vivian Mello
Author-email: vmellomasc@gmail.com
Classifier: Development Status :: 3 - Alpha
Classifier: Intended Audience :: Science/Research
Classifier: Topic :: Scientific/Engineering :: Bio-Informatics
Classifier: License :: OSI Approved :: MIT License
Classifier: Programming Language :: Python :: 3.8
Classifier: Programming Language :: Python :: 3.9
Classifier: Programming Language :: Python :: 3.10
Classifier: Programming Language :: Python :: 3.11
Classifier: Programming Language :: Python :: 3.12
Classifier: Programming Language :: Python :: 3.13
Requires-Python: >=3.8
License-File: LICENSE
Requires-Dist: pandas
Requires-Dist: numpy
Requires-Dist: polars
Requires-Dist: biom-format
Requires-Dist: bioservices
Requires-Dist: scipy
Requires-Dist: scikit-learn
Requires-Dist: statsmodels
Requires-Dist: scikit-bio
Requires-Dist: patsy
Requires-Dist: boruta
Requires-Dist: matplotlib
Requires-Dist: seaborn
Requires-Dist: plotly
Requires-Dist: pyyaml
Requires-Dist: tqdm
Requires-Dist: appdirs
Requires-Dist: setuptools
Requires-Dist: psutil
Requires-Dist: requests
Provides-Extra: dev
Requires-Dist: pytest>=8.0; extra == "dev"
Requires-Dist: pytest-cov>=4.0; extra == "dev"
Requires-Dist: pytest-mock>=3.12; extra == "dev"
Requires-Dist: build; extra == "dev"
Requires-Dist: twine; extra == "dev"
Dynamic: author
Dynamic: author-email
Dynamic: classifier
Dynamic: description
Dynamic: description-content-type
Dynamic: home-page
Dynamic: license-file
Dynamic: provides-extra
Dynamic: requires-dist
Dynamic: requires-python
Dynamic: summary
